corner/__init__.py
corner/arviz_corner.py
corner/core.py
corner/corner.py
corner/version.py
corner-2.2.2.dist-info/LICENSE
corner-2.2.2.dist-info/METADATA
corner-2.2.2.dist-info/WHEEL
corner-2.2.2.dist-info/top_level.txt
corner-2.2.2.dist-info/RECORD
