Metadata-Version: 2.1
Name: corner
Version: 2.2.2
Summary: Make some beautiful corner plots
Author-email: Dan Foreman-Mackey <foreman.mackey@gmail.com>
License: BSD 2-Clause License
Project-URL: Homepage, https://corner.readthedocs.io
Project-URL: Source, https://github.com/dfm/corner.py
Project-URL: Bug Tracker, https://github.com/dfm/corner.py/issues
Classifier: Operating System :: OS Independent
Classifier: Programming Language :: Python :: 3
Classifier: Development Status :: 5 - Production/Stable
Classifier: License :: OSI Approved :: BSD License
Requires-Python: >=3.9
Provides-Extra: test
Provides-Extra: arviz
Provides-Extra: docs
License-File: LICENSE
